alfrd/__init__.py
alfrd/lib.py
alfrd/util.py
alfrd-0.0.5.dist-info/LICENSE
alfrd-0.0.5.dist-info/METADATA
alfrd-0.0.5.dist-info/WHEEL
alfrd-0.0.5.dist-info/entry_points.txt
alfrd-0.0.5.dist-info/top_level.txt
alfrd-0.0.5.dist-info/RECORD
