Metadata-Version: 2.1
Name: alfrd
Version: 0.0.5
Summary: Automated Logical FRamework for Dynamic script execution(ALFRD)
Home-page: https://github.com/avialxee/alfrd/
Author: Avinash Kumar
Author-email: avialxee@gmail.com
Project-URL: Bug Tracker, https://github.com/avialxee/alfrd/issues
Classifier: Programming Language :: Python :: 3
Classifier: Programming Language :: Python :: 3.6
Classifier: Programming Language :: Python :: 3.7
Classifier: Programming Language :: Python :: 3.8
Classifier: License :: OSI Approved :: BSD License
Classifier: Intended Audience :: Science/Research
License-File: LICENSE
Requires-Dist: google-api-python-client
Requires-Dist: google-auth-httplib2
Requires-Dist: google-auth-oauthlib
Requires-Dist: gspread
Requires-Dist: gspread-formatting
Requires-Dist: pandas
Requires-Dist: numpy
Requires-Dist: psutil
Requires-Dist: protobuf ==3.19.6
Provides-Extra: dev
Requires-Dist: pytest >=3.7 ; extra == 'dev'
